README.rst
mcareader.py
setup.cfg
setup.py
mcareader.egg-info/PKG-INFO
mcareader.egg-info/SOURCES.txt
mcareader.egg-info/dependency_links.txt
mcareader.egg-info/entry_points.txt
mcareader.egg-info/requires.txt
mcareader.egg-info/top_level.txt